zerodb_server-0.1.25-py3.5-nspkg.pth
zerodb_server-0.1.25.dist-info/DESCRIPTION.rst
zerodb_server-0.1.25.dist-info/METADATA
zerodb_server-0.1.25.dist-info/RECORD
zerodb_server-0.1.25.dist-info/WHEEL
zerodb_server-0.1.25.dist-info/entry_points.txt
zerodb_server-0.1.25.dist-info/metadata.json
zerodb_server-0.1.25.dist-info/namespace_packages.txt
zerodb_server-0.1.25.dist-info/top_level.txt
zerodbext/server/__init__.py
zerodbext/server/api.py
zerodbext/server/manage.py
zerodbext/server/run.py
