Metadata-Version: 1.0
Name: zerodb-server
Version: 0.1.25
Summary: ZeroDB server
Home-page: http://zerodb.io
Author: ZeroDB Inc.
Author-email: michael@zerodb.io
License: AGPLv3
Platform: UNKNOWN
